Metadata-Version: 1.0
Name: marcopolo-probability
Version: 1.0
Summary: Gaussian and Binomial distributions
Home-page: UNKNOWN
Author: Marco Polo Leyva Rios
Author-email: UNKNOWN
License: UNKNOWN
Platform: UNKNOWN
